patientflow/README.md
patientflow/__init__.py
patientflow/_version.py
patientflow/aggregate.py
patientflow/errors.py
patientflow/evaluate.py
patientflow/generate.py
patientflow/load.py
patientflow/model_artifacts.py
patientflow/prepare.py
patientflow/survival_curve.py
patientflow/calculate/__init__.py
patientflow/calculate/admission_in_prediction_window.py
patientflow/calculate/arrival_rates.py
patientflow/calculate/survival_curve.py
patientflow/model-input/consults-mapping.csv
patientflow/model-input/reporting_hierarchy.csv
patientflow/predict/__init__.py
patientflow/predict/emergency_demand.py
patientflow/predictors/README.md
patientflow/predictors/__init__.py
patientflow/predictors/incoming_admission_predictors.py
patientflow/predictors/sequence_to_outcome_predictor.py
patientflow/predictors/value_to_outcome_predictor.py
patientflow/train/__init__.py
patientflow/train/classifiers.py
patientflow/train/emergency_demand.py
patientflow/train/incoming_admission_predictor.py
patientflow/train/sequence_predictor.py
patientflow/train/utils.py
patientflow/viz/__init__.py
patientflow/viz/arrival_rates.py
patientflow/viz/aspirational_curve.py
patientflow/viz/calibration.py
patientflow/viz/data_distribution.py
patientflow/viz/epudd.py
patientflow/viz/estimated_probabilities.py
patientflow/viz/features.py
patientflow/viz/madcap.py
patientflow/viz/observed_against_expected.py
patientflow/viz/probability_distribution.py
patientflow/viz/quantile_quantile.py
patientflow/viz/randomised_pit.py
patientflow/viz/shap.py
patientflow/viz/survival_curve.py
patientflow/viz/trial_results.py
patientflow/viz/utils.py
patientflow-1.0.5.dist-info/licenses/LICENSE.md
patientflow-1.0.5.dist-info/METADATA
patientflow-1.0.5.dist-info/WHEEL
patientflow-1.0.5.dist-info/top_level.txt
patientflow-1.0.5.dist-info/RECORD
