Metadata-Version: 2.4
Name: patientflow
Version: 1.0.5
Summary: Code and explanatory notebooks for predicting short-term hospital bed capacity using real-time data
Author-email: Zella King <zella.king@ucl.ac.uk>
License: # MIT License
Project-URL: homepage, https://github.com/zmek/patientflow
Classifier: Operating System :: POSIX
Classifier: Programming Language :: Python :: 3
Classifier: Programming Language :: Python :: 3 :: Only
Classifier: Programming Language :: Python :: 3.10
Classifier: Programming Language :: Python :: 3.11
Classifier: Programming Language :: Python :: 3.12
Classifier: Programming Language :: Python :: 3.13
Classifier: Typing :: Typed
Requires-Python: >=3.10
License-File: LICENSE.md
Requires-Dist: PyYAML==6.0.2
Requires-Dist: joblib>=1.4.2
Requires-Dist: matplotlib>=3.1.3
Requires-Dist: numpy>=1.18.1
Requires-Dist: pandas>=1.0.1
Requires-Dist: requests
Requires-Dist: scikit-learn>=1.4.0
Requires-Dist: scipy>=1.4.1
Requires-Dist: seaborn>=0.10.0
Requires-Dist: sympy>=1.12
Requires-Dist: tabulate==0.9.0
Requires-Dist: xgboost>=2.0.3
Provides-Extra: dev
Requires-Dist: build; extra == "dev"
Requires-Dist: mypy; extra == "dev"
Requires-Dist: pre-commit; extra == "dev"
Requires-Dist: ruff; extra == "dev"
Requires-Dist: tox; extra == "dev"
Requires-Dist: twine; extra == "dev"
Provides-Extra: docs
Requires-Dist: griffe; extra == "docs"
Requires-Dist: mkdocs; extra == "docs"
Requires-Dist: mkdocs-autorefs; extra == "docs"
Requires-Dist: mkdocs-awesome-pages-plugin; extra == "docs"
Requires-Dist: mkdocs-include-markdown-plugin; extra == "docs"
Requires-Dist: mkdocs-material; extra == "docs"
Requires-Dist: mkdocstrings; extra == "docs"
Requires-Dist: mkdocstrings-python; extra == "docs"
Requires-Dist: nbconvert; extra == "docs"
Provides-Extra: test
Requires-Dist: pytest; extra == "test"
Requires-Dist: pytest-cov; extra == "test"
Requires-Dist: pyyaml; extra == "test"
Dynamic: license-file
